CHANGELOG.rst
README.rst
gentools/__init__.py
gentools/core.py
gentools/types.py
gentools/utils.py
gentools-1.2.1.dist-info/LICENSE
gentools-1.2.1.dist-info/METADATA
gentools-1.2.1.dist-info/WHEEL
gentools-1.2.1.dist-info/RECORD
