Metadata-Version: 2.1
Name: gentools
Version: 1.2.1
Summary: Tools for generators, generator functions, and generator-based coroutines
Home-page: https://github.com/ariebovenberg/gentools
License: MIT
Keywords: generators,itertools,coroutines
Author: Arie Bovenberg
Author-email: a.c.bovenberg@gmail.com
Requires-Python: >=3.7,<4.0
Classifier: Development Status :: 5 - Production/Stable
Classifier: License :: OSI Approved :: MIT License
Classifier: Programming Language :: Python :: 3
Classifier: Programming Language :: Python :: 3.7
Classifier: Programming Language :: Python :: 3.8
Classifier: Programming Language :: Python :: 3.9
Classifier: Programming Language :: Python :: 3.10
Classifier: Programming Language :: Python :: 3.11
Classifier: Programming Language :: Python :: 3.10
Classifier: Programming Language :: Python :: 3.11
Classifier: Programming Language :: Python :: 3.7
Classifier: Programming Language :: Python :: 3.8
Classifier: Programming Language :: Python :: 3.9
Classifier: Topic :: Software Development :: Libraries :: Python Modules
Requires-Dist: importlib-metadata ; python_version < "3.8"
Project-URL: Repository, https://github.com/ariebovenberg/gentools
